LICENSE
README.md
pyproject.toml
setup.py
src/edit_tool/__init__.py
src/edit_tools.egg-info/PKG-INFO
src/edit_tools.egg-info/SOURCES.txt
src/edit_tools.egg-info/dependency_links.txt
src/edit_tools.egg-info/top_level.txt