Metadata-Version: 2.2
Name: edit_tools
Version: 0.1
Summary: edit tool
Home-page: https://packaging.python.org/specifications/core-metadata
Author: ZZW
Author-email: zhouziwei@eastmoney.com
Requires-Python: >=3.6
License-File: LICENSE
Dynamic: author
Dynamic: author-email
Dynamic: description
Dynamic: description-content-type
Dynamic: home-page
Dynamic: requires-python
Dynamic: summary
